README.md
setup.py
bin/filter.py
ufo_filter/__init__.py
ufo_filter.egg-info/PKG-INFO
ufo_filter.egg-info/SOURCES.txt
ufo_filter.egg-info/dependency_links.txt
ufo_filter.egg-info/top_level.txt
ufo_filter.egg-info/zip-safe