Metadata-Version: 1.0
Name: ufo-filter
Version: 1.2
Summary: Functional text substitution system
Home-page: https://github.com/rjbalest/ufo-filter.git
Author: Russell Balest
Author-email: russell@balest.com
License: MIT
Platform: UNKNOWN
